biofefi/.streamlit/config.toml
biofefi/Home.py
biofefi/__init__.py
biofefi/components/__init__.py
biofefi/components/configuration.py
biofefi/components/experiments.py
biofefi/components/forms.py
biofefi/components/images/__init__.py
biofefi/components/images/logos.py
biofefi/components/logs.py
biofefi/components/plots.py
biofefi/components/preprocessing.py
biofefi/feature_importance/feature_importance.py
biofefi/feature_importance/fuzzy.py
biofefi/feature_importance/fuzzy_interpretation.py
biofefi/feature_importance/interpreter.py
biofefi/launch.py
biofefi/machine_learning/data.py
biofefi/machine_learning/learner.py
biofefi/machine_learning/models/__init__.py
biofefi/machine_learning/models/nn_models.py
biofefi/machine_learning/models/nn_networks.py
biofefi/machine_learning/models/svm.py
biofefi/machine_learning/train.py
biofefi/options/__init__.py
biofefi/options/choices/__init__.py
biofefi/options/choices/metrics.py
biofefi/options/choices/ml_models.py
biofefi/options/choices/ui.py
biofefi/options/enums.py
biofefi/options/execution.py
biofefi/options/fi.py
biofefi/options/file_paths.py
biofefi/options/fuzzy.py
biofefi/options/ml.py
biofefi/options/plotting.py
biofefi/options/preprocessing.py
biofefi/options/search_grids.py
biofefi/pages/1_New_Experiment.py
biofefi/pages/2_Data_Preprocessing.py
biofefi/pages/3_Data_Visualisation.py
biofefi/pages/4_Train_Models.py
biofefi/pages/5_Feature_Importance.py
biofefi/pages/6_View_Experiments.py
biofefi/pages/__init__.py
biofefi/services/__init__.py
biofefi/services/configuration.py
biofefi/services/experiments.py
biofefi/services/feature_importance/__init__.py
biofefi/services/feature_importance/ensemble_methods.py
biofefi/services/feature_importance/global_methods.py
biofefi/services/feature_importance/local_methods.py
biofefi/services/feature_importance/results.py
biofefi/services/logs.py
biofefi/services/machine_learning/__init__.py
biofefi/services/machine_learning/results.py
biofefi/services/metrics.py
biofefi-1.1.1.dist-info/LICENSE
biofefi-1.1.1.dist-info/METADATA
biofefi-1.1.1.dist-info/WHEEL
biofefi-1.1.1.dist-info/entry_points.txt
biofefi-1.1.1.dist-info/RECORD
