Metadata-Version: 2.3
Name: biofefi
Version: 1.1.1
Summary: 
Author: Daniel Lea
Author-email: Daniel.Lea@nottingham.ac.uk
Requires-Python: >=3.11,<3.13
Classifier: Programming Language :: Python :: 3
Classifier: Programming Language :: Python :: 3.11
Classifier: Programming Language :: Python :: 3.12
Requires-Dist: lime (==0.2.0.1)
Requires-Dist: matplotlib (==3.8.2)
Requires-Dist: numpy (==1.26.4)
Requires-Dist: pandas (==2.2.2)
Requires-Dist: scikit-fuzzy (==0.4.2)
Requires-Dist: scikit-learn (==1.5.2)
Requires-Dist: seaborn (==0.13.2)
Requires-Dist: shap (==0.45.0)
Requires-Dist: streamlit (==1.36)
Requires-Dist: torch (>=2.5.1,<3.0.0)
Requires-Dist: tqdm (==4.66.2)
Requires-Dist: xgboost (==2.1.0)
